{
  "agreement_target": 327,
  "best_any_profile": {
    "assignment_seed": 88231,
    "assignment_strategy": "fiber_block",
    "basis_class_indices": [
      0,
      1,
      2,
      3,
      4,
      6
    ],
    "basis_id": "basisaware_0_1_2_3_4_6",
    "basis_support_sizes": [
      253,
      253,
      253,
      253,
      179,
      74
    ],
    "candidate_order": 54,
    "coordinate_classes_hash": "511ff4d464eee11f75458e6dc2e3a0d93cd31a950fc92b12e13265359d426675",
    "coordinate_collision_groups": 0,
    "coordinate_duplicate_excess": 0,
    "dependency_positive": true,
    "dependency_score": 19,
    "exact_collision_positive": true,
    "exact_collision_score": -91,
    "forced_functional_identities": 0,
    "formal_nullity_lower_bound": 0,
    "functional_classes": 12,
    "functional_span_rank": 6,
    "matrix_shape": [
      512,
      271
    ],
    "max_functional_support": 253,
    "max_pair_count": 253,
    "max_raw_collision_multiplicity": 253,
    "mutation_id": null,
    "nested_support_pairs": 1,
    "pair7_counts": [
      253,
      253,
      253,
      253,
      253
    ],
    "pairdiff_collision_excess": 0,
    "pairdiff_collision_groups": 0,
    "prescribed_collision_realized": true,
    "profile_kind": "natural",
    "profile_order": 4,
    "q_variable_budget_ok": false,
    "q_variable_count": 271,
    "q_variable_floor": 350,
    "raw_collision_excess": 1765,
    "raw_collision_groups": 12,
    "raw_functional_rows": 1777,
    "repeated_coordinate_groups": 0,
    "repeated_coordinate_pairs": 0,
    "repeated_coordinate_rows": 0,
    "repeated_support_coordinate_groups": 0,
    "repeated_support_coordinate_pairs": 0,
    "repeated_support_coordinate_rows": 0,
    "repeated_support_groups": 1,
    "repeated_support_pairs": 1,
    "repeated_support_rows": 2,
    "row_minus_col": 241,
    "row_surplus": 241,
    "selected_count_hash": "04348011ce0bce938ed25264214f9c3eded7fe0116c02b14e32451eb5839f090",
    "source_system_order": 20,
    "support_collision_groups": 1,
    "support_coordinate_collision_groups": 0,
    "support_coordinate_duplicate_excess": 0,
    "support_duplicate_excess": 1,
    "support_overlap_nonzero_pairs": 3,
    "support_overlap_total": 148,
    "support_vector": [
      327,
      327,
      327,
      327,
      327,
      327,
      327
    ],
    "template_id": "lcodesign_0003_basis_simple",
    "unique_coordinate_rows": 6,
    "unique_support_coordinate_pairs": 6,
    "unique_support_hashes": 5
  },
  "best_candidate": null,
  "best_collision_q_budget_profile": null,
  "best_exact_collision_profile": {
    "assignment_seed": 88231,
    "assignment_strategy": "fiber_block",
    "basis_class_indices": [
      0,
      1,
      2,
      3,
      4,
      6
    ],
    "basis_id": "basisaware_0_1_2_3_4_6",
    "basis_support_sizes": [
      253,
      253,
      253,
      253,
      179,
      74
    ],
    "candidate_order": 54,
    "coordinate_classes_hash": "511ff4d464eee11f75458e6dc2e3a0d93cd31a950fc92b12e13265359d426675",
    "coordinate_collision_groups": 0,
    "coordinate_duplicate_excess": 0,
    "dependency_positive": true,
    "dependency_score": 19,
    "exact_collision_positive": true,
    "exact_collision_score": -91,
    "forced_functional_identities": 0,
    "formal_nullity_lower_bound": 0,
    "functional_classes": 12,
    "functional_span_rank": 6,
    "matrix_shape": [
      512,
      271
    ],
    "max_functional_support": 253,
    "max_pair_count": 253,
    "max_raw_collision_multiplicity": 253,
    "mutation_id": null,
    "nested_support_pairs": 1,
    "pair7_counts": [
      253,
      253,
      253,
      253,
      253
    ],
    "pairdiff_collision_excess": 0,
    "pairdiff_collision_groups": 0,
    "prescribed_collision_realized": true,
    "profile_kind": "natural",
    "profile_order": 4,
    "q_variable_budget_ok": false,
    "q_variable_count": 271,
    "q_variable_floor": 350,
    "raw_collision_excess": 1765,
    "raw_collision_groups": 12,
    "raw_functional_rows": 1777,
    "repeated_coordinate_groups": 0,
    "repeated_coordinate_pairs": 0,
    "repeated_coordinate_rows": 0,
    "repeated_support_coordinate_groups": 0,
    "repeated_support_coordinate_pairs": 0,
    "repeated_support_coordinate_rows": 0,
    "repeated_support_groups": 1,
    "repeated_support_pairs": 1,
    "repeated_support_rows": 2,
    "row_minus_col": 241,
    "row_surplus": 241,
    "selected_count_hash": "04348011ce0bce938ed25264214f9c3eded7fe0116c02b14e32451eb5839f090",
    "source_system_order": 20,
    "support_collision_groups": 1,
    "support_coordinate_collision_groups": 0,
    "support_coordinate_duplicate_excess": 0,
    "support_duplicate_excess": 1,
    "support_overlap_nonzero_pairs": 3,
    "support_overlap_total": 148,
    "support_vector": [
      327,
      327,
      327,
      327,
      327,
      327,
      327
    ],
    "template_id": "lcodesign_0003_basis_simple",
    "unique_coordinate_rows": 6,
    "unique_support_coordinate_pairs": 6,
    "unique_support_hashes": 5
  },
  "best_profile": null,
  "candidate": {
    "agreement_vector": null,
    "codeword_hashes": null,
    "constructed": false,
    "received_word_hash": null,
    "seven_distinct": false
  },
  "denominator": "17^32",
  "exact_rowcollision_search": {
    "basis_profiles_constructed": 540,
    "best_any_q_variable_count": 271,
    "best_any_repeated_coordinate_pairs": 0,
    "best_any_repeated_support_coordinate_pairs": 0,
    "best_any_repeated_support_pairs": 1,
    "best_exact_collision_q_variable_count": 271,
    "best_exact_collision_score": -91,
    "best_failure_mode": "EXACT_ROWCOLLISION_Q_BUDGET_FAIL",
    "best_proxy_nullity": null,
    "best_proxy_rank": null,
    "best_q_budget_collision_q_variable_count": null,
    "best_q_budget_collision_score": null,
    "best_q_variable_count": null,
    "candidate_collision_group_counts": {
      "support": 60
    },
    "candidates_scanned": 60,
    "candidates_with_collision_groups": 60,
    "exact_collision_profiles": 438,
    "exact_collision_q_budget_profiles": 0,
    "forced_groups_per_candidate": 8,
    "forced_profiles_constructed": 60,
    "max_systems": 360,
    "max_templates": 128,
    "natural_basis_profiles_per_candidate": 8,
    "natural_profiles_constructed": 480,
    "natural_random_bases": 512,
    "profile_candidate_limit": 60,
    "profile_failure_counts": {},
    "profile_rank_limit": 12,
    "proxy_positive_profiles": 0,
    "proxy_prime": 12289,
    "proxy_ranked_profiles": 0,
    "q_budget_profiles": 36,
    "q_variable_floor": 350,
    "structural_pass_systems": 360
  },
  "mca_counted": false,
  "not_claimed": [
    "MCA N_bad",
    "protocol soundness",
    "ordinary list decoding beyond stated interleaved-list predicate",
    "global Lambda_mu(C,327) <= 6",
    "exact Lambda_mu",
    "exact delta*_C",
    "Sage GF(17^32) exact lift",
    "MCA/protocol consequence from this list-track proxy",
    "global obstruction outside the tested ledger-codesign exact-rowcollision front"
  ],
  "previous_rowdependency_search": {
    "basis_profiles_constructed": 160,
    "best_proxy_nullity": 0,
    "best_proxy_rank": 771,
    "commit": "b74ba9e",
    "dependency_q_budget_profiles": 18,
    "failure_mode": "ROWDEP_PROXY_FULL_RANK",
    "proof_status": "EXACT_EXTRACTION_NO_A327 / ROWDEP_PROXY_FULL_RANK / PARTIAL / EXPERIMENTAL",
    "proxy_positive_profiles": 0,
    "proxy_ranked_profiles": 12,
    "structural_pass_systems": 240
  },
  "proof_status": "EXACT_EXTRACTION_NO_A327 / EXACT_ROWCOLLISION_Q_BUDGET_FAIL / PARTIAL / EXPERIMENTAL",
  "proxy_ranked_profiles": [],
  "row": "RS[F_17^32,H,256]",
  "source_commit": "b74ba9e",
  "track": "INTERLEAVED_LIST"
}
